pplog/__init__.py
pplog/azure/__init__.py
pplog/azure/azure.py
pplog/config/__init__.py
pplog/config/config.py
pplog/config/defaults.py
pplog/config/parser.py
pplog/config/utils.py
pplog/dbricks/__init__.py
pplog/dbricks/cached_workspace_client.py
pplog/dbricks/dbu_table.py
pplog/dbricks/model.py
pplog/dbu_estimation/__init__.py
pplog/errors/__init__.py
pplog/errors/decorator.py
pplog/factory/__init__.py
pplog/formatters/__init__.py
pplog/handlers/__init__.py
pplog/handlers/splunk_databricks.py
pplog/handlers/splunk_handler.py
pplog/hooks/__init__.py
pplog/hooks/boolean.py
pplog/hooks/databricks_job.py
pplog/hooks/dataframe.py
pplog/hooks/fastapi.py
pplog/hooks/float.py
pplog/hooks/job_exception.py
pplog/integrations/__init__.py
pplog/integrations/great_expectations/__init__.py
pplog/integrations/http/__init__.py
pplog/log_checks/__init__.py
pplog/log_checks/_base.py
pplog/log_checks/check_model.py
pplog/log_checks/log_checks.py
pplog/ppconf/ppconf.yaml
pplog/time_tracking/__init__.py
pplog/unhandled_exception/__init__.py
pplog-0.1.41.dist-info/METADATA
pplog-0.1.41.dist-info/WHEEL
pplog-0.1.41.dist-info/RECORD
