Metadata-Version: 2.1
Name: pplog
Version: 0.1.41
Summary: Pricing Domain Logging and Monitoring Tool
Home-page: https://dev.azure.com/schwarzit/schwarzit.ai-public/_git/pplog
Author: Paolo Andreas Stall Rechia
Author-email: paolo_andreas.stall_rechia@mail.schwarz
Maintainer: Paolo Andreas Stall Rechia
Maintainer-email: paolo_andreas.stall_rechia@mail.schwarz
Requires-Python: >=3.8,<4.0
Classifier: Programming Language :: Python :: 3
Classifier: Programming Language :: Python :: 3.8
Classifier: Programming Language :: Python :: 3.9
Classifier: Programming Language :: Python :: 3.10
Classifier: Programming Language :: Python :: 3.11
Classifier: Programming Language :: Python :: 3.12
Requires-Dist: azure-eventgrid (>=4.16.0,<5.0.0)
Requires-Dist: azure-identity (>=1.15.0,<2.0.0)
Requires-Dist: databricks-sdk (>=0.18.0,<0.19.0)
Requires-Dist: logstash-formatter (>=0.5.17,<0.6.0)
Requires-Dist: omegaconf (>=2.3.0,<3.0.0)
Requires-Dist: pyhocon (==0.3.59)
Requires-Dist: pyspark (>=3.3.2)
Project-URL: Repository, https://dev.azure.com/schwarzit/schwarzit.ai-public/_git/pplog
